{"lang_id": "tr", "grams": [{"description": "1grams", "contents": [["a", 37390187], ["e", 29986311], ["i", 27869288], ["n", 23918032], ["r", 23025214], ["l", 22747750], ["ı", 13975571], ["k", 12996276], ["d", 12938169], ["t", 12365236], ["s", 10883647], ["m", 10861281], ["u", 9926053], ["o", 9732233], ["y", 9331718], ["b", 5689711], ["ü", 5216899], ["ş", 4362566], ["g", 3932810], ["z", 3886699], ["v", 3767886], ["h", 3348141], ["c", 3267812], ["p", 2940995], ["ç", 2896381], ["ğ", 2836485], ["ö", 2209227], ["f", 1967229], ["A", 1613244], ["B", 1592502], ["T", 1349352], ["K", 1337278], ["S", 1306518], ["M", 1171042], ["D", 901999], ["E", 794963], ["C", 709277], ["H", 665425], ["P", 660570], ["G", 654324], ["İ", 611218], ["O", 527209], ["F", 522054], ["Y", 516554], ["N", 475653], ["R", 451518], ["L", 450783], ["j", 317818], ["I", 315534], ["U", 308053], ["w", 301530], ["ý", 294965], ["V", 285806], ["Ş", 219911], ["W", 205545], ["J", 205192], ["Ç", 192022], ["Ö", 190199], ["x", 140435], ["Ü", 127797], ["â", 106956], ["Z", 100240], ["þ", 97422], ["ð", 65842], ["î", 65092], ["X", 40661], ["é", 38663], ["q", 33757], ["а", 21705], ["Q", 21229], ["о", 17664], ["á", 15381], ["û", 14695], ["е", 14332], ["и", 13579], ["Ý", 11391], ["н", 10716], ["р", 10373], ["ó", 9851], ["í", 9683], ["Ä", 9137], ["ä", 8872], ["с", 8568], ["ا", 8341], ["к", 8058], ["ə", 7808], ["т", 7784], ["л", 7180], ["в", 6946], ["è", 6223], ["ć", 5978], ["ō", 5577], ["Ğ", 4823], ["у", 4649], ["д", 4564], ["ر", 4227], ["ل", 4203], ["м", 3844], ["ن", 3781], ["š", 3776], ["ы", 3679], ["й", 3491], ["Ÿ", 3397], ["ñ", 3300], ["م", 3212], ["α", 3210], ["г", 3076], ["Þ", 2886], ["č", 2791], ["ā", 2774], ["و", 2741], ["ú", 2417], ["ب", 2298], ["د", 2159], ["ë", 2064], ["Å", 671], ["ŋ", 652], ["É", 599], ["י", 317], ["ł", 53], ["à", 52], ["ã", 49], ["ي", 38], ["я", 34], ["ο", 33], ["ê", 33], ["М", 31], ["ß", 31], ["ø", 31], ["б", 31], ["ū", 30], ["з", 29], ["ă", 27], ["ч", 27], ["п", 27], ["С", 25], ["å", 25], ["ه", 25], ["ь", 25], ["ô", 24], ["х", 23], ["Š", 22], ["А", 22], ["ï", 22], ["س", 22], ["П", 21], ["ش", 21], ["ع", 20], ["ت", 19], ["ی", 18], ["Â", 18], ["К", 17], ["ρ", 17], ["γ", 16], ["ς", 16], ["ν", 16], ["Р", 16], ["э", 16], ["æ", 16], ["ц", 15], ["ա", 15], ["ح", 15], ["ń", 14], ["ė", 14], ["Н", 14], ["μ", 14], ["ί", 13], ["Г", 13], ["ة", 13], ["đ", 13], ["ò", 13], ["ι", 13], ["县", 13], ["Ə", 12], ["ю", 12], ["ق", 12], ["Х", 12], ["Đ", 12], ["τ", 11], ["В", 11], ["Т", 11], ["ī", 11], ["ի", 11], ["ш", 11], ["ج", 11], ["ș", 11], ["õ", 11], ["ω", 10], ["σ", 10], ["λ", 10], ["Ž", 10], ["ž", 10], ["О", 10], ["Ł", 10], ["ʿ", 10], ["Á", 10], ["أ", 10], ["ك", 10], ["ε", 9], ["ი", 9], ["ә", 9], ["ʼ", 9], ["ḥ", 9], ["ж", 9], ["Ō", 9], ["Б", 9], ["υ", 9], ["동", 8], ["ř", 8], ["ր", 8], ["Л", 8], ["ف", 8], ["ո", 8], ["π", 7], ["κ", 7], ["ż", 7], ["خ", 7], ["洞", 7], ["の", 7], ["կ", 7], ["Ś", 7], ["ー", 7], ["Č", 7], ["ה", 7], ["پ", 7], ["区", 7], ["א", 7], ["ʾ", 7], ["η", 6], ["ک", 6], ["ф", 6], ["Я", 6], ["ź", 6], ["ר", 6], ["ē", 6], ["ě", 6], ["ъ", 6], ["ő", 6], ["θ", 6], ["И", 6], ["У", 6], ["і", 6], ["ე", 6], ["ز", 6], ["β", 6], ["º", 6], ["처", 6], ["ւ", 6], ["Ð", 5], ["Θ", 5], ["Е", 5], ["ј", 5], ["ʘ", 5], ["ა", 5], ["公", 5], ["З", 5], ["Π", 5], ["Д", 5], ["ש", 5], ["מ", 5], ["ו", 5], ["수", 5], ["δ", 5], ["ì", 5], ["城", 5], ["Μ", 5], ["ص", 5], ["մ", 5], ["յ", 5], ["ό", 4], ["Î", 4], ["Δ", 4], ["警", 4], ["ą", 4], ["ң", 4], ["ㄨ", 4], ["տ", 4], ["ę", 4], ["ל", 4], ["ם", 4], ["Ú", 4], ["ύ", 4], ["ё", 4], ["غ", 4], ["έ", 4], ["Ф", 4], ["Ш", 4], ["성", 4], ["市", 4], ["Β", 4], ["Ā", 4], ["ǐ", 4], ["ב", 4], ["ώ", 4], ["ն", 4], ["נ", 4], ["Κ", 3], ["Γ", 3], ["Ħ", 3], ["ù", 3], ["Ч", 3], ["Ј", 3], ["隊", 3], ["Ó", 3], ["ო", 3], ["Ц", 3], ["щ", 3], ["स", 3], ["क", 3], ["र", 3], ["ű", 3], ["Э", 3], ["ラ", 3], ["バ", 3], ["ד", 3], ["ח", 3], ["Ա", 3], ["궁", 3], ["ө", 3], ["ע", 3], ["南", 3], ["ק", 3], ["현", 3], ["Ю", 3], ["山", 3], ["成", 3], ["김", 3], ["神", 3], ["新", 3], ["φ", 3], ["ś", 3], ["Ć", 3], ["œ", 3], ["Ν", 3], ["산", 3], ["族", 3], ["自", 3], ["治", 3], ["ή", 3], ["ạ", 3], ["建", 3], ["中", 3], ["ク", 3], ["گ", 3], ["µ", 3], ["行", 3], ["음", 3], ["럼", 3], ["ウ", 3], ["Α", 3], ["ǎ", 3], ["區", 3], ["人", 3], ["ǧ", 3], ["म", 3], ["ț", 2], ["ň", 2], ["ल", 2], ["ά", 2], ["Ω", 2], ["麻", 2], ["上", 2], ["備", 2], ["航", 2], ["路", 2], ["რ", 2], ["დ", 2], ["ბ", 2], ["一", 2], ["を", 2], ["І", 2], ["և", 2], ["Պ", 2], ["ჩ", 2], ["კ", 2], ["त", 2], ["ᑦ", 2], ["星", 2], ["ى", 2], ["夏", 2], ["文", 2], ["莽", 2], ["眉", 2], ["ầ", 2], ["ộ", 2], ["ར", 2], ["川", 2], ["ן", 2], ["פ", 2], ["井", 2], ["Í", 2], ["英", 2], ["공", 2], ["소", 2], ["ル", 2], ["Є", 2], ["Ж", 2], ["ї", 2], ["Щ", 2], ["大", 2]], "total": 385747408}, {"description": "2grams", "contents": [["n ", 7288344], ["e ", 6710889], ["ar", 5919331], ["a ", 5561480], ["an", 5536795], ["la", 5390578], ["er", 5253473], ["i ", 4936235], ["le", 4743541], ["r ", 4643541], ["in", 4618727], ["en", 3567505], [" b", 3544329], ["de", 3446037], ["ı ", 3399143], ["da", 3326211], ["il", 3272139], ["ın", 3257575], ["nd", 3201653], ["ir", 3182249], ["ri", 3044810], ["k ", 3032234], ["ra", 2970035], ["al", 2889197], [" k", 2847829], ["ma", 2800822], ["li", 2751122], ["ya", 2730149], [" d", 2576950], [" y", 2509899], ["ak", 2443301], [" a", 2436077], [" s", 2385312], [" i", 2321905], ["ta", 2244844], ["ol", 2116440], ["bi", 2074045], ["ve", 2049696], ["ka", 2035970], ["si", 2021006], [" v", 2005821], ["di", 2004966], [" o", 2000546], ["el", 1987163], ["te", 1926374], ["ti", 1887911], ["me", 1884715], ["ay", 1877009], [" g", 1874576], ["ni", 1865105], ["re", 1838890], ["ek", 1828731], ["on", 1809513], ["ne", 1780159], [" t", 1761636], ["u ", 1710510], ["lı", 1699161], ["et", 1697730], ["rı", 1671033], ["na", 1660765], ["as", 1655555], ["es", 1640679], ["un", 1628002], ["ad", 1596704], ["nı", 1565049], ["m ", 1515295], ["at", 1506483], ["am", 1484553], ["dı", 1442875], ["ki", 1435769], [" e", 1422013], ["sı", 1415569], ["or", 1412332], ["ik", 1400268], ["ıl", 1391335], ["is", 1381089], ["sa", 1375981], ["ır", 1368839], ["l ", 1345365], ["mi", 1307016], ["ye", 1285030], ["t ", 1259383], ["ed", 1240596], ["ul", 1207186], ["st", 1190071], ["ur", 1175888], ["ba", 1160062], [" A", 1159337], ["im", 1154031], ["kl", 1146349], ["iy", 1142633], ["em", 1129794], ["rd", 1128405], ["ha", 1125046], ["nl", 1121011], [" B", 1108938], ["lm", 1093285], ["tı", 1064267], ["se", 1052806], [" m", 1045948], ["ge", 1043926], ["aş", 1039084], ["rl", 1012857], ["ll", 1007539], ["lu", 993642], [" h", 972338], ["ld", 960672], ["kt", 944110], ["ke", 919453], ["ün", 913691], [" K", 910456], [" S", 909163], ["yo", 901656], [" M", 899059], ["nu", 885544], ["s ", 873893], ["yı", 855812], ["ür", 836171], ["ey", 831822], ["iş", 831190], ["it", 822554], [" T", 811511], ["şt", 810658], ["bu", 802772], ["ru", 797180], ["iz", 775865], ["ap", 772411], ["z ", 770160], ["ış", 765031], [" ç", 763650], ["ca", 747996], ["ık", 744395], ["rk", 743408], ["ği", 737379], ["az", 730068], ["mı", 721473], ["nc", 716333], ["ce", 711818], ["gi", 708397], ["ah", 703640], ["ım", 693003], ["du", 690965], ["ku", 676051], ["be", 668898], ["rt", 661115], ["va", 653772], ["kı", 635698], ["yl", 633774], ["ğı", 629326], ["ze", 625190], ["ağ", 613335], [" D", 610245], ["çi", 596391], [" ö", 595442], ["ro", 592223], ["nt", 591941], ["ev", 584176], ["rm", 581007], ["ab", 570076], ["hi", 566173], ["çe", 564289], ["um", 560330], [" p", 556469], ["ok", 551140], ["ko", 544843], ["ş ", 543323], ["us", 542647], ["za", 542630], ["ml", 542274], ["so", 538999], ["iç", 532948], [" f", 527614], ["pa", 518352], ["to", 517624], ["he", 510916], ["ön", 507886], [" H", 506787], ["dü", 504662], ["ör", 501735], ["id", 500704], [" E", 493753], ["şa", 492112], ["y ", 491941], ["tl", 490355], ["Ka", 480730], ["gö", 479263], ["iğ", 479147], ["şı", 478598], [" G", 477801], [" P", 476743], ["tu", 475801], ["om", 473819], ["ng", 472413], ["üz", 471855], [" ş", 467993], ["ns", 466644], [" İ", 460548], ["su", 459136], ["ü ", 456157], ["ac", 453177], ["mu", 439810], ["ça", 439317], ["zi", 439023], ["nm", 438150], ["lo", 437716], ["ci", 433599], ["ül", 425069], [" ü", 422949], ["Ma", 422380], ["şi", 421817], ["lü", 421053], ["ğu", 418612], ["ığ", 418433], ["eş", 414480], [" C", 409003], ["eğ", 403240], ["rs", 396390], ["üm", 393620], ["af", 390968], ["p ", 390277], ["ec", 390148], ["d ", 389121], ["ük", 383216], ["os", 383208], ["yü", 381297], [" Y", 380703], ["tt", 377412], ["şl", 376020], [" F", 372200], [" n", 368600], ["ız", 367488], ["o ", 366794], ["tü", 365983], [" u", 361889], ["Bu", 361156], ["av", 356079], [" l", 355979], ["fa", 351879], ["do", 351269], ["lk", 349746], ["yi", 344273], [" O", 344068], ["şe", 338717], ["ıs", 337884], ["Ba", 336366], ["ez", 335228], ["tr", 335127], ["lt", 332534], ["tm", 332262], ["lg", 330663], ["mü", 330160], ["yn", 330108], ["şm", 329230], ["çı", 326655], ["aç", 325078], [" L", 322674], ["uş", 321744], ["uz", 321110], ["vi", 320585], ["rü", 318953], ["ıy", 317250], ["ğl", 316502], [" R", 314212], ["oğ", 311945], ["ut", 308482], ["ic", 307067], ["gü", 306639], ["nü", 305818], ["pl", 299893], ["Ha", 298711], ["eb", 297758], [" r", 297194], ["yu", 294712], ["Sa", 294651], ["uğ", 293181], ["uk", 286463], ["fi", 286325], ["op", 285309], ["cı", 284938], ["oy", 282952], ["uy", 276249], ["zl", 275738], [" N", 275557], ["cu", 272024], ["eç", 268779], ["ih", 267985], ["öy", 267725], ["zı", 266936], ["ks", 265966], ["ig", 264847], ["ip", 263707], ["öl", 261958], ["po", 261486], ["pı", 259000], ["no", 258756], [" c", 257015], ["sy", 255233], ["ib", 254953], ["pe", 247896], ["ğr", 247591], ["sl", 246750], ["bo", 246715], ["ço", 245191], ["üy", 243970], [" U", 243326], ["ga", 237117], ["Bi", 236592], ["öz", 233449], [" z", 232735], ["ny", 232577], ["ç ", 230494], ["ot", 229714], ["yd", 229615], ["fe", 224405], ["rg", 224366], ["Al", 223809], ["bü", 222447], ["kü", 219861], ["Be", 219044], ["sk", 211801], ["Tü", 210230], ["ef", 209825], ["nr", 207059], ["th", 206346], ["sü", 204935], ["To", 204266], ["ai", 204072], ["üş", 204066], ["f ", 204035], ["ia", 203718], ["up", 203512], ["An", 203045], ["De", 202019], ["h ", 201883], ["eh", 201824], ["fı", 199300], ["kç", 198613], ["şk", 197345], ["gr", 196565], ["Me", 193170], [" V", 193040], ["Ya", 192374], ["if", 188286], ["rn", 188209], ["pi", 186528], ["md", 184117], ["mo", 183285], ["Pa", 180186], ["Ta", 179560], ["iv", 177445], ["pr", 176612], ["Se", 175372], ["ıc", 174531], ["ıd", 174424], ["co", 174394], ["yr", 174382], ["ch", 173884], ["nk", 170818], [" Ş", 170608], ["dd", 170321], ["ğe", 167662], [" I", 166731], ["sp", 165605], ["fo", 164748], ["gu", 163001], ["Ar", 160880], ["od", 160787], ["Ko", 160605], ["Ku", 160232], ["g ", 158789], ["rç", 158647], ["Te", 158380], ["pt", 158353], ["ou", 157337], [" J", 157216], ["io", 155113], ["mp", 154927], ["Ge", 153403], ["ie", 152274], ["ly", 151901], ["ep", 151373], ["ud", 151166], ["kö", 151055], ["ub", 150742], ["vr", 150431], ["İs", 149055], ["oc", 148230], ["sm", 146772], ["dö", 146153], ["üs", 145832], ["km", 145327], [" W", 144787], ["ea", 144486], ["çl", 143720], ["ry", 140613], ["ss", 140310], [" Ç", 140259], ["lç", 139790], ["rb", 138915], ["zd", 136541]], "total": 385747408}, {"description": "3grams", "contents": [["lar", 2309077], ["an ", 2105222], ["ler", 1942933], ["eri", 1804188], ["da ", 1726945], [" ve", 1692700], ["in ", 1565633], ["ir ", 1529387], ["de ", 1478679], ["nda", 1474784], [" bi", 1458197], ["en ", 1448397], ["ve ", 1436726], ["arı", 1362472], ["ara", 1339154], [" ol", 1262047], [" ya", 1189629], ["bir", 1170727], ["er ", 1159444], ["lan", 1157347], [" ka", 1139461], ["ınd", 1104698], ["ile", 1036293], ["nde", 965544], ["ın ", 936822], ["esi", 931393], ["ası", 885367], [" de", 877628], ["ak ", 864957], ["ini", 854744], ["ar ", 845837], ["rin", 845361], ["le ", 842896], ["ind", 814989], [" ta", 793912], ["anı", 777299], [" il", 763154], [" ge", 742620], [" ba", 730950], ["ola", 710294], ["ili", 699253], ["ını", 685009], ["n b", 681805], ["ri ", 676715], ["ele", 668906], [" sa", 661261], ["ne ", 659008], ["den", 645731], ["edi", 632018], ["dan", 628457], ["si ", 621519], ["ama", 617591], ["sin", 617187], ["ala", 614542], ["ya ", 612519], [" bu", 608933], ["e b", 603021], ["nin", 596096], [" da", 592468], ["rın", 591513], ["na ", 585359], ["eni", 571749], [" al", 569349], ["ni ", 560794], ["ine", 556473], ["li ", 555946], ["ki ", 554389], ["sın", 548126], ["nla", 542036], ["nın", 539807], ["adı", 537320], ["rak", 535991], ["aya", 531382], ["dır", 531347], ["nı ", 528736], [" ha", 523150], ["len", 512351], ["a b", 511867], ["rı ", 511627], ["alı", 511267], ["dir", 505255], ["ik ", 504556], ["ada", 504011], ["ır ", 503562], ["ere", 494194], ["ek ", 485070], ["lı ", 481178], ["bil", 478718], ["ard", 471318], ["lma", 469472], [" gö", 465137], [" ku", 455709], ["tar", 453098], ["man", 452772], ["ayı", 450328], ["ede", 447217], ["eti", 445473], ["ılı", 444329], [" te", 443817], [" iç", 439802], ["anl", 436090], [" so", 434219], ["un ", 431687], ["n k", 431353], ["tir", 430934], ["eli", 429614], ["yap", 427427], ["sı ", 426959], ["iye", 425975], ["la ", 425402], ["e k", 422727], ["tan", 421180], ["ıla", 417505], [" ye", 417097], ["onu", 416904], ["ana", 414244], ["and", 411736], ["isi", 410341], ["kle", 406251], ["ra ", 405245], ["ma ", 404771], ["n s", 404257], ["on ", 399553], ["ter", 398744], ["a d", 396905], ["e d", 391405], ["yıl", 391352], ["n d", 390518], ["iği", 390211], ["kar", 389327], ["ığı", 387181], ["n y", 385385], ["a k", 385325], ["ist", 384550], ["mak", 383283], ["i b", 382376], ["kla", 382161], ["im ", 378847], ["lik", 376864], [" se", 374811], ["rle", 372304], ["n a", 372030], ["yor", 372020], ["e y", 370913], ["lla", 366990], ["mas", 366351], ["lam", 364989], ["ulu", 364900], ["ste", 361634], ["n i", 358713], ["içi", 357121], [" ko", 356357], ["re ", 355306], ["son", 354806], ["el ", 352190], ["unu", 351952], [" ar", 348812], ["ye ", 347059], ["e s", 345597], ["e g", 345077], ["ilm", 342355], ["ali", 342136], ["çin", 342048], ["iri", 341108], ["ına", 340391], ["eme", 339472], ["ver", 339151], [" yı", 338032], [" Ma", 337437], ["yan", 336696], ["eki", 336180], ["tır", 335694], ["ık ", 329257], ["et ", 329043], ["baş", 328689], ["mış", 326492], ["a g", 325329], [" ma", 323860], ["lık", 323741], ["eği", 323051], ["n  ", 322761], ["ari", 320217], ["al ", 318295], ["yle", 318108], [" be", 313716], ["kta", 313243], ["e i", 312280], ["r a", 309858], ["a y", 308970], ["şti", 307659], ["ene", 307584], ["bul", 307075], ["aha", 305846], [" Ka", 305832], ["e  ", 303004], ["mek", 301388], ["ekt", 300685], ["ran", 300290], ["akt", 299367], ["miş", 298205], ["i v", 297172], ["kul", 295388], ["end", 294373], [" an", 293613], ["kan", 292850], ["lle", 292424], ["di ", 291729], ["gör", 290824], ["ştı", 290779], ["ndi", 290617], ["ğı ", 288629], [" di", 288431], ["gel", 288186], ["atı", 287852], [" is", 286718], ["a s", 285750], ["bu ", 284847], ["nun", 283710], ["e a", 280923], ["lin", 280612], ["i k", 280538], ["und", 279742], [" gi", 279638], ["i i", 279082], ["olu", 278278], ["yer", 277957], ["te ", 277307], ["i a", 276654], ["rek", 275462], ["kte", 275021], ["ren", 274919], [" ed", 274821], ["ken", 274101], [" et", 273826], ["ekl", 272946], [" me", 272760], ["emi", 272441], ["sta", 272277], [" Ba", 272036], ["i y", 271929], ["erl", 271885], ["ldu", 268855], ["rla", 268801], ["der", 268739], ["lın", 268530], ["oru", 268466], ["uru", 267903], ["imi", 267731], ["lir", 266961], ["n g", 265468], ["iyo", 264411], ["dı ", 263881], ["ras", 262626], ["n o", 262114], ["  y", 261952], ["öne", 261214], ["old", 260998], ["ula", 260682], ["uğu", 260462], ["ı b", 260413], ["tur", 260375], ["dil", 259472], ["a i", 259340], ["at ", 258539], ["ği ", 257573], ["raf", 256760], ["i d", 256493], ["i o", 256023], ["n t", 255509], ["ril", 255254], ["nle", 255130], ["üze", 254050], ["aki", 254030], ["irl", 252816], ["art", 252497], ["yon", 252161], ["ağl", 251877], ["aşı", 251323], ["ece", 250483], ["erd", 250011], ["rdı", 249265], ["nu ", 249171], ["n e", 248390], ["r v", 247685], ["nce", 247109], ["ce ", 245050], ["ikl", 244784], ["rma", 244771], [" Ha", 244606], ["apı", 244486], [" ad", 242886], ["san", 241634], ["mes", 241109], [" Bu", 239753], ["işt", 239082], ["kon", 237958], ["ldı", 237546], [" ke", 237467], ["kal", 237395], ["mal", 237228], ["me ", 237187], ["ağı", 235362], ["ım ", 234956], ["nan", 234574], ["cak", 233533], ["ta ", 233201], ["ur ", 233118], [" Sa", 232530], ["k b", 232373], ["yla", 230605], ["ışt", 230237], [" dü", 230224], ["i s", 230222], ["akı", 229896], [" va", 228663], ["ark", 228348], ["olm", 227894], ["r k", 227786], ["rke", 227742], ["ı i", 226709], ["rde", 226269], ["min", 226098], ["ull", 225996], ["yar", 225838], ["mi ", 225746], ["n v", 225524], ["e e", 224752], ["ger", 224169], ["şma", 222906], ["e o", 222264], ["iz ", 221721], [" şe", 221211], ["eye", 220809], [" gü", 220522], ["r B", 220147], [" he", 219933], ["rum", 219906], ["ayn", 219821], ["a a", 219738], ["yna", 219641], ["tle", 219068], ["ün ", 218169], ["men", 217682], ["e t", 217160], ["lun", 216934], ["ı v", 216917], ["ret", 216873], ["ısı", 216605], [" do", 213446], ["aşa", 213084], ["lem", 212769], ["k k", 211876], ["akl", 211668], ["k i", 211646], ["ok ", 211284], ["am ", 210345], ["arl", 210304], [" ça", 210229], ["iya", 209464], ["var", 209432], ["ğin", 208317], ["lay", 208243], ["şla", 207274], ["rda", 206974], ["ürk", 206773], ["tin", 206751], ["ans", 206410], ["hal", 206144], ["r b", 205742], ["ı s", 205277], [" yo", 204529], ["Bu ", 204493], ["ımı", 204197], ["kad", 203722], ["r  ", 203533], ["nma", 203496], ["let", 202458], [" ön", 202362], [" ço", 202008], ["mad", 201761], [" ay", 201690], ["yet", 201620], ["se ", 201550], ["kat", 200458], ["ral", 200454], ["ent", 200150], ["tim", 199139], [" ki", 198774], ["mle", 198726], ["ild", 198679], ["or ", 198548], ["ı o", 198245], ["ılm", 198130], ["ell", 197100], ["ca ", 197087], ["abi", 196973], ["r d", 196156], ["lu ", 195986], ["rme", 195442], ["amı", 195179]], "total": 385747408}, {"description": "4grams", "contents": [[" ve ", 1387461], [" bir", 1112834], ["ında", 1078270], ["leri", 1065951], ["ları", 1004409], ["nda ", 924996], ["bir ", 865707], ["inde", 759876], ["erin", 715310], ["nde ", 604246], [" ola", 596401], ["arın", 567363], ["dan ", 566076], ["nin ", 558265], ["eri ", 551072], ["lar ", 478389], ["den ", 476328], ["arı ", 472028], ["ler ", 470769], ["ine ", 467604], ["lara", 445808], ["nın ", 443990], ["lan ", 425747], ["arak", 425094], ["rak ", 418728], ["esi ", 410992], [" yap", 401933], ["asın", 390885], ["ini ", 379876], ["ndan", 378905], ["    ", 377814], ["ile ", 374763], [" ile", 365935], ["inin", 364026], ["esin", 362717], [" tar", 350943], ["iler", 350123], ["nlar", 347614], [" içi", 334270], ["ası ", 334041], ["için", 330100], [" yıl", 325404], ["olar", 324531], ["ması", 319000], ["n bi", 315471], ["ını ", 314675], ["eler", 304557], [" baş", 303692], [" son", 300471], ["alar", 299122], ["ına ", 291631], ["anla", 285279], [" de ", 285137], [" gör", 284124], ["ştir", 276434], ["çin ", 274827], ["anın", 272161], [" da ", 267527], [" bu ", 263860], [" kar", 259406], ["sınd", 253426], ["dır ", 250315], ["ının", 249671], ["i ve", 241898], ["endi", 240450], ["ştır", 235892], ["oldu", 235607], ["lanı", 232073], ["işti", 231146], ["rini", 229226], [" old", 228316], ["ıştı", 225126], [" gel", 224974], ["bili", 224450], ["r ve", 223073], ["dir ", 222915], ["lama", 220751], [" yer", 220382], ["ığı ", 220354], [" olm", 220182], ["ardı", 219471], ["aya ", 216267], [" bil", 215398], ["lık ", 214026], ["olan", 213242], ["klar", 212952], ["ulla", 212814], [" ara", 212625], [" ver", 211899], ["e ka", 210791], [" bul", 210291], ["iği ", 208542], ["kler", 207489], ["ılar", 206988], ["an b", 206104], ["n ya", 205917], ["yapı", 205368], ["rind", 205204], ["yılı", 204638], ["da b", 203086], [" kul", 201837], ["  yı", 201762], ["sind", 200453], [" ger", 200397], ["i ol", 200218], ["akta", 200057], ["erle", 199500], ["rin ", 199065], ["a ka", 197784], ["llan", 197197], ["rası", 195634], ["i bi", 194946], ["rler", 194476], ["e ya", 194366], ["mesi", 192758], ["ada ", 192055], ["mışt", 191745], ["unda", 190521], [" olu", 189991], ["ı ve", 189854], ["nden", 189636], ["adır", 188026], ["Türk", 186584], ["rın ", 184241], ["ılın", 183506], ["sini", 183459], ["ulun", 183300], ["kull", 183297], ["bulu", 182576], ["lard", 182279], ["ekle", 182213], ["tara", 182090], ["nun ", 181348], [" değ", 181143], ["makt", 180458], ["erek", 179736], ["e bi", 179373], ["a da", 178439], ["olma", 178053], ["ilgi", 177941], ["a bi", 177377], ["ilir", 176659], ["duğu", 176657], ["aki ", 176621], ["en b", 176477], ["lınd", 176099], [" kon", 176030], ["alan", 174782], ["n ve", 174740], ["sını", 174641], ["enin", 174539], ["onra", 174496], ["rını", 170802], ["araf", 170159], ["iste", 169649], [" var", 169635], ["mişt", 169285], ["ara ", 168830], ["edir", 168729], ["ikle", 167957], ["arda", 167901], ["len ", 167824], ["çok ", 167619], ["cak ", 167520], ["aha ", 166318], ["e ba", 166145], ["ayna", 166110], ["iyor", 165799], ["sonr", 165151], ["lik ", 164979], [" Tür", 164946], ["liği", 164794], [" edi", 164702], ["de b", 164565], ["iye ", 163793], ["isi ", 162459], ["ktad", 162349], ["a ya", 162306], ["mler", 162265], ["daki", 161591], ["dığı", 161141], ["tadı", 160411], [" kur", 159176], ["e de", 159069], ["eden", 159011], ["ı ol", 158991], ["edil", 158582], ["e ge", 157859], ["eki ", 157597], ["yla ", 157591], ["rafı", 157473], ["arih", 157316], ["andı", 156394], ["aşla", 156242], ["ekte", 155478], ["tler", 155396], ["rınd", 154470], ["afın", 153401], [" dah", 153392], ["yle ", 153250], ["göre", 153083], ["fınd", 151830], ["mak ", 150994], ["stan", 150903], ["nan ", 150528], ["anı ", 150480], ["n so", 150330], ["erde", 150261], ["land", 150059], ["aras", 149944], ["rine", 149799], ["ere ", 149640], ["e bu", 149638], ["akla", 148899], ["lerd", 148895], ["abil", 148707], ["n ka", 148675], ["an  ", 148479], ["lığı", 148387], ["n ol", 148211], ["isin", 146705], ["iğin", 146068], ["mekt", 145059], ["ynak", 144282], [" ala", 144211], ["etme", 144025], ["anlı", 143785], ["unu ", 143087], ["anda", 143051], ["man ", 142289], ["lduğ", 141953], ["sine", 141644], ["ildi", 141118], ["a ba", 141061], ["tesi", 140593], ["kada", 139806], ["a ge", 139577], [" kad", 139478], ["ilmi", 139013], [" çal", 138507], ["alış", 138465], ["uğu ", 138371], ["arla", 138173], ["da y", 138093], [" kal", 137921], ["tır ", 137585], ["daha", 137514], ["ilme", 136782], ["deği", 136700], ["başl", 136566], [" çok", 136510], [" geç", 136329], [" yar", 136028], ["diği", 135937], ["n ge", 135861], ["ışma", 135666], ["tan ", 135512], ["önem", 135116], ["in b", 135036], ["ı bi", 134814], ["ığın", 134738], ["yan ", 134708], ["maya", 134511], ["ilen", 134310], [" ilk", 134102], ["nra ", 133774], ["ağla", 133592], [" sür", 132485], ["a ve", 131952], ["ama ", 131154], ["n ba", 131075], ["eni ", 130980], ["de y", 130870], ["ıkla", 130516], ["tari", 130121], ["aman", 130012], ["tedi", 129854], ["k ve", 129750], ["ibi ", 129625], ["n de", 129299], ["uştu", 129285], ["apıl", 129260], ["er a", 128820], ["erke", 128179], ["e il", 127554], ["konu", 127363], [" Bu ", 127065], ["mala", 126875], ["leme", 126801], ["çalı", 126562], ["orum", 126403], ["eye ", 126332], ["deki", 126215], ["lmas", 125795], [" en ", 125542], [" bağ", 125475], ["onun", 125423], [" kat", 125397], ["enle", 125085], ["tir ", 124572], ["ayan", 124357], ["ılma", 124247], ["etle", 124183], ["ede ", 124179], ["irle", 123895], ["ıyla", 123863], ["irli", 123444], ["kara", 122990], ["rlar", 122849], [" yaz", 122812], ["an s", 122520], ["e sa", 122403], ["ıldı", 122322], [" say", 121992], [" çık", 121426], ["yoru", 121317], [" kay", 121265], ["ise ", 121263], ["idir", 121214], ["llar", 120416], [" gün", 120322], ["etti", 120144], ["ılan", 119932], ["i ya", 119928], ["unun", 119559], ["r al", 119386], ["syon", 118676], ["ir k", 118517], ["mek ", 118483], ["eril", 118206], ["rda ", 118191], ["üzer", 117571], ["üyük", 117537], ["da k", 117459], ["lanm", 117422], [" yön", 117225], ["nler", 116482], ["ster", 116190], [" üze", 115810], [" ken", 115271], ["likl", 115211], ["an k", 115119], ["k bi", 115069], ["mış ", 115054], ["ller", 114949], ["ağlı", 114065], ["e ve", 113800], ["aldı", 113739], ["ayı ", 113668], [" iki", 113496], ["alı ", 112871], [" Mar", 112705], ["iril", 112699], ["ilin", 112400], [" açı", 112316], [" yaş", 112294], ["gibi", 112062], [" gib", 111887], [" tak", 111883], ["ştur", 111768], ["mlar", 111709], [" ist", 111679], [" bel", 111500], ["öğre", 111129], ["i de", 111092], ["ili ", 110868], ["rdır", 110796], ["da d", 110738], ["in k", 110007], ["lmiş", 109874], ["ayın", 109675], ["ledi", 109624], [" dön", 109556], ["öyle", 109263], ["ve b", 109028], ["lmak", 108856], ["iyle", 108749], ["ünde", 108407], [" böl", 108270], [" sağ", 108129], ["kted", 107884], [" ede", 107794], ["Kayn", 107712], ["ilk ", 107695], [" top", 107575], ["alle", 107570], ["akım", 107439], ["veri", 107024], ["yeni", 106933], ["i ka", 106902], ["dar ", 106860], ["uğun", 106794], ["urul", 106788], ["lmış", 106598], ["arşı", 105900], ["le b", 105837], ["anma", 105775], ["ana ", 105357], ["etim", 104983], ["alig", 104887]], "total": 385747408}, {"description": "5grams", "contents": [[" bir ", 844866], ["ında ", 683495], ["inde ", 518429], ["lerin", 518099], ["ların", 516398], ["leri ", 415261], ["ları ", 402594], ["arak ", 394883], ["ndan ", 370647], ["inin ", 356900], [" ile ", 331309], [" için", 327450], ["larak", 325688], ["ından", 308342], ["olara", 299094], [" olar", 297013], ["n bir", 275316], ["için ", 269723], ["sında", 253099], ["     ", 249618], ["ının ", 243554], [" oldu", 228009], ["asınd", 211396], ["iştir", 209685], ["i ve ", 206876], [" olan", 206612], ["erini", 204169], ["rinde", 203659], ["  yıl", 201698], ["sinde", 197921], ["olan ", 193380], ["mıştı", 191494], [" yılı", 189283], ["erind", 188861], ["ıştır", 187750], ["anın ", 184128], ["nden ", 183494], ["ullan", 183238], ["kulla", 182507], [" yapı", 181832], ["ileri", 180448], ["r ve ", 178789], [" bulu", 177625], ["arın ", 175166], [" olma", 174673], ["makta", 174618], ["yılın", 174307], [" kull", 174254], ["nları", 171768], ["eleri", 171069], [" tara", 170714], ["erin ", 169972], ["aları", 168255], ["lında", 167605], ["taraf", 167567], ["bulun", 166871], ["mişti", 166285], ["arını", 165733], ["sonra", 165104], [" sonr", 164912], [" Türk", 162054], ["anlar", 161045], ["ı ve ", 160662], ["tadır", 156972], ["enin ", 156154], ["ktadı", 155939], ["ması ", 155835], ["inden", 153447], ["i bir", 152984], ["rafın", 152526], ["arınd", 151907], [" göre", 151658], ["ılınd", 151552], ["fında", 150403], ["rında", 149557], ["arafı", 148715], ["afınd", 148038], ["daki ", 147495], ["larda", 147356], ["rine ", 146239], ["aynak", 143998], ["e bir", 142329], ["lduğu", 141903], ["aktad", 140566], ["llanı", 140326], ["erine", 137907], ["esind", 135975], ["kları", 135555], ["arası", 135188], [" başl", 135170], ["unda ", 135018], ["olduğ", 134477], [" deği", 134127], ["n ve ", 134086], ["onra ", 133727], ["bilir", 133479], ["kleri", 133171], ["mekte", 132948], [" çok ", 132094], [" daha", 131792], ["rasın", 131727], ["daha ", 131689], ["masın", 127493], ["a bir", 127389], ["sine ", 126187], ["n son", 125287], [" konu", 125257], [" çalı", 125004], ["lerde", 124890], ["deki ", 124287], [" tari", 124275], [" edil", 122953], ["ıyla ", 122809], ["malar", 121762], ["çalış", 121671], ["yapıl", 121260], ["tarih", 120818], ["başla", 119311], ["rini ", 117554], ["lması", 116967], ["a da ", 116496], [" üzer", 115654], ["an bi", 115498], [" alan", 115257], [" gibi", 111743], ["uştur", 111141], ["i ola", 110428], ["likle", 110159], ["ştır ", 109518], ["ardır", 109374], ["tedir", 109283], ["eden ", 108643], ["k ve ", 108385], ["iyle ", 108033], ["ktedi", 107697], ["Kayna", 107685], ["gibi ", 107240], [" ilk ", 107130], ["ekted", 106462], [" ve b", 106428], ["unun ", 106178], ["etler", 106115], ["ikler", 105143], ["align", 104285], ["ılan ", 104254], [" ise ", 103835], [" aras", 103447], ["nda b", 103362], ["  UTC", 103231], ["arda ", 101994], [" büyü", 101759], ["bir k", 101484], ["rinin", 101237], ["dığı ", 101215], ["a ve ", 101162], ["ilgil", 100886], ["mesi ", 100419], [" bağl", 100377], ["ilen ", 100193], [" sağl", 100167], ["adır ", 99487], ["asını", 99381], ["esini", 99168], ["ayan ", 98396], ["nakça", 98286], ["ynakç", 98192], [" kada", 97543], [" veri", 97503], ["esine", 97500], ["kadar", 97369], ["mleri", 97249], ["zaman", 97174], ["landı", 96966], ["karşı", 96495], [" karş", 96406], ["duğu ", 96375], [" gere", 96327], [" zama", 95981], ["ilmiş", 95780], ["erler", 95716], [" ve s", 94993], ["tleri", 94971], [" vard", 94844], ["vardı", 93806], ["adar ", 93741], [" görü", 93185], ["üyük ", 93116], [" yer ", 92925], ["rleri", 92878], [" anla", 92830], ["lara ", 92442], ["nlar ", 92413], ["erek ", 92166], ["ı bir", 92136], ["lendi", 91916], [" kuru", 91527], ["iler ", 91425], ["arihi", 91396], ["yorum", 91018], ["kendi", 89924], ["ı ola", 89187], [" kend", 88938], ["ştir ", 88459], [" oluş", 88386], ["k bir", 88324], ["erde ", 88206], [" öğre", 87889], ["er al", 87868], ["ilir ", 87860], ["rını ", 87848], ["büyük", 87823], ["gerek", 87811], [" biri", 87563], ["liği ", 87257], ["abili", 86767], [" geli", 86593], ["Türki", 86084], [" yeni", 86012], [" birl", 85290], ["rkiye", 85197], ["bilgi", 85123], ["maya ", 85079], ["ürkiy", 85064], ["en bi", 84956], [" bilg", 84656], ["lanıl", 84327], ["e ve ", 83942], ["zerin", 83620], ["halle", 83484], ["ıları", 83385], [" orta", 82348], ["asyon", 82345], ["üzeri", 82286], [" ve k", 81888], ["edir ", 81833], [" takı", 81485], ["ahall", 81190], ["ndaki", 81048], ["nde b", 80762], ["k içi", 80760], ["lere ", 80597], ["birli", 80316], ["imler", 79155], ["da bi", 79136], [" süre", 78942], ["takım", 78816], ["sinin", 78342], [" long", 77825], ["yer a", 77752], [" kara", 77404], ["tesi ", 76919], [" ilgi", 76847], ["öster", 76772], [" yapm", 76760], [" yöne", 76712], ["aklar", 76590], ["sini ", 76557], [" sahi", 76540], ["idir ", 76483], ["sına ", 76317], ["diği ", 76162], ["ğini ", 75318], ["rının", 75284], [" topl", 75243], [" etti", 75111], ["alışm", 75099], ["rdır ", 75081], [" yaşa", 74929], ["leşti", 74868], ["göste", 74747], ["ncak ", 74596], [" göst", 74590], [" düze", 74575], ["aşkan", 74424], ["iğini", 74082], ["i ile", 73906], ["anda ", 73595], ["erkez", 73501], [" sıra", 73389], [" madd", 73203], [" sonu", 73176], ["da ya", 73166], ["lığı ", 72961], [" bili", 72842], ["lanma", 72568], [" yayı", 72558], ["ılmış", 72527], [" etki", 72133], ["duğun", 72068], ["irlik", 72059], ["alan ", 72059], ["madde", 72005], ["nda y", 71718], ["versi", 71659], ["e de ", 71653], [" ve d", 71502], [" gele", 71492], [" önce", 71343], ["tiril", 71243], [" yapt", 71097], ["lları", 71074], ["lışma", 70976], ["veya ", 70952], ["ıklar", 70776], ["mesin", 70597], ["erçek", 70454], ["lmişt", 70342], ["lama ", 70333], ["de bu", 70293], [" oyun", 70155], ["ekler", 70115], ["dan b", 70071], ["anan ", 69961], ["de ya", 69938], ["bir s", 69912], [" ilçe", 69888], ["r Bu ", 69847], [" veya", 69782], [" kişi", 69674], ["rına ", 69447], ["uğunu", 69412], ["yaptı", 69385], ["arına", 69095], ["sını ", 68979], ["ğını ", 68946], ["sağla", 68918], [" sayı", 68886], [" etme", 68758], [" film", 68631], ["apıla", 68492], ["onlar", 68127], ["yrıca", 67869], [" döne", 67673], ["muştu", 67533], [" iki ", 67358], ["adığı", 67298], ["unlar", 67276], [" iste", 67167], ["rıca ", 67118], ["liğin", 67093], ["ünde ", 66667], ["adan ", 66654], ["ivers", 66503], ["eştir", 66498], ["göre ", 66447], ["nde y", 66311], [" düşü", 66304], ["değiş", 66139], ["bir a", 66132], ["lmesi", 66131], [" içer", 66128], [" alig", 66027], ["eler ", 66026], [" açık", 66023], ["endir", 65979], ["niver", 65955], ["istem", 65858], ["likte", 65851], ["veril", 65841], [" gerç", 65820], ["gerçe", 65804], [" yıll", 65583], [" her ", 65564], ["cente", 65553], [" önem", 65417], ["ığını", 65363], ["a baş", 65310], [" katı", 65295], [" özel", 65257], [" kaza", 65198], ["e baş", 65197], ["ğitim", 65156], [" ayrı", 64995], ["ndeki", 64706], ["den b", 64692], ["değil", 64639], ["asına", 64528], ["  tar", 64497], ["evlet", 64283], ["ellik", 64183], ["edilm", 64118], [" çıka", 64115], ["ştiri", 64032], ["lmışt", 64010], ["görev", 63903], [" beli", 63878], ["rada ", 63819], ["ındak", 63715], ["nda k", 63661], [" söyl", 63582], ["belir", 63548], ["kurul", 63527], ["a gör", 63495], ["lığın", 63477], ["ersit", 63302], ["alar ", 63252], ["ar ve", 62822], ["ılar ", 62768], ["labil", 62707], ["er ve", 62485]], "total": 385747408}]}